{"overall_ratio_based": {"rbg": {"eu": {"alliance": {"lowest": 17805, "rival": {"rating": 1904, "rank": 1785}, "challenger": {"rating": 1675, "rank": 6255}, "rank_one": {"rating": "2728", "rank": 19}, "duelist": {"rating": 2202, "rank": 535}, "glad": {"rating": "2583", "rank": 90}}, "horde": {"lowest": 17630, "rival": {"rating": 1906, "rank": 1766}, "challenger": {"rating": 1676, "rank": 6217}, "rank_one": {"rating": "2694", "rank": 19}, "duelist": {"rating": 2205, "rank": 529}, "glad": {"rating": "2582", "rank": 90}}}, "us": {"alliance": {"lowest": 11024, "rival": {"rating": 1915, "rank": 1103}, "challenger": {"rating": 1696, "rank": 3860}, "rank_one": {"rating": "2756", "rank": 12}, "duelist": {"rating": 2180, "rank": 331}, "glad": {"rating": "2661", "rank": 56}}, "horde": {"lowest": 18166, "rival": {"rating": 1816, "rank": 1828}, "challenger": {"rating": 1639, "rank": 6361}, "rank_one": {"rating": "2694", "rank": 19}, "duelist": {"rating": 2068, "rank": 548}, "glad": {"rating": "2582", "rank": 91}}}}, "3v3": {"eu": {"alliance": {"lowest": 85603, "rival": {"rating": 1913, "rank": 8578}, "challenger": {"rating": 1659, "rank": 30016}, "rank_one": {"rating": "2801", "rank": 87}, "duelist": {"rating": 2181, "rank": 2576}, "glad": {"rating": "2581", "rank": 429}}, "horde": {"lowest": 87304, "rival": {"rating": 1909, "rank": 8748}, "challenger": {"rating": 1655, "rank": 30660}, "rank_one": {"rating": "2790", "rank": 90}, "duelist": {"rating": 2177, "rank": 2625}, "glad": {"rating": "2576", "rank": 438}}}, "us": {"alliance": {"lowest": 50963, "rival": {"rating": 1925, "rank": 5121}, "challenger": {"rating": 1686, "rank": 17861}, "rank_one": {"rating": "2844", "rank": 51}, "duelist": {"rating": 2181, "rank": 1531}, "glad": {"rating": "2665", "rank": 256}}, "horde": {"lowest": 71989, "rival": {"rating": 1854, "rank": 7221}, "challenger": {"rating": 1625, "rank": 25315}, "rank_one": {"rating": "2811", "rank": 72}, "duelist": {"rating": 2106, "rank": 2169}, "glad": {"rating": "2608", "rank": 361}}}}}, "current": {"rbg": {"eu": {"horde": {"lowest": 6530, "rival": {"rating": 2025, "rank": 657}, "challenger": {"rating": 1777, "rank": 2287}, "rank_one": {"rating": "2836", "rank": 7}, "duelist": {"rating": 2293, "rank": 197}, "glad": {"rating": "2689", "rank": 33}}, "alliance": {"lowest": 9460, "rival": {"rating": 2060, "rank": 951}, "challenger": {"rating": 1775, "rank": 3316}, "rank_one": {"rating": "2802", "rank": 10}, "duelist": {"rating": 2355, "rank": 285}, "glad": {"rating": "2673", "rank": 48}}, "combined": {"count": 18827}}, "us": {"horde": {"lowest": 10761, "rival": {"rating": 1921, "rank": 1077}, "challenger": {"rating": 1699, "rank": 3778}, "rank_one": {"rating": "2787", "rank": 11}, "duelist": {"rating": 2190, "rank": 323}, "glad": {"rating": "2651", "rank": 54}}, "alliance": {"lowest": 9367, "rival": {"rating": 2063, "rank": 939}, "challenger": {"rating": 1777, "rank": 3289}, "rank_one": {"rating": "2787", "rank": 10}, "duelist": {"rating": 2357, "rank": 282}, "glad": {"rating": "2673", "rank": 47}}, "combined": {"count": 17291}}}, "3v3": {"eu": {"horde": {"lowest": 21816, "rival": {"rating": 2105, "rank": 2184}, "challenger": {"rating": 1843, "rank": 7664}, "rank_one": {"rating": "2915", "rank": 22}, "duelist": {"rating": 2343, "rank": 658}, "glad": {"rating": "2766", "rank": 110}}, "alliance": {"lowest": 29050, "rival": {"rating": 2148, "rank": 2914}, "challenger": {"rating": 1874, "rank": 10188}, "rank_one": {"rating": "2901", "rank": 30}, "duelist": {"rating": 2430, "rank": 872}, "glad": {"rating": "2734", "rank": 147}}, "combined": {"count": 58677}}, "us": {"horde": {"lowest": 30817, "rival": {"rating": 2031, "rank": 3097}, "challenger": {"rating": 1777, "rank": 10798}, "rank_one": {"rating": "2820", "rank": 31}, "duelist": {"rating": 2274, "rank": 926}, "glad": {"rating": "2721", "rank": 155}}, "alliance": {"lowest": 29627, "rival": {"rating": 2143, "rank": 2964}, "challenger": {"rating": 1870, "rank": 10374}, "rank_one": {"rating": "2820", "rank": 30}, "duelist": {"rating": 2425, "rank": 889}, "glad": {"rating": "2721", "rank": 149}}, "combined": {"count": 52633}}}}, "overall": {"rbg": {"eu": {"lowest": 35436, "rival": {"rating": 1761, "rank": 3548}, "challenger": {"rating": 1592, "rank": 12429}, "rank_one": {"rating": 2687, "rank": 36}, "duelist": {"rating": 2030, "rank": 1064}, "glad": {"rating": 2438, "rank": 179}}, "us": {"lowest": 29191, "rival": {"rating": 1736, "rank": 2920}, "challenger": {"rating": 1586, "rank": 10260}, "rank_one": {"rating": 2565, "rank": 30}, "duelist": {"rating": 1962, "rank": 880}, "glad": {"rating": 2346, "rank": 146}}}, "3v3": {"eu": {"lowest": 172908, "rival": {"rating": 1764, "rank": 17299}, "challenger": {"rating": 1533, "rank": 60687}, "rank_one": {"rating": 2713, "rank": 173}, "duelist": {"rating": 2020, "rank": 5201}, "glad": {"rating": 2431, "rank": 866}}, "us": {"lowest": 122953, "rival": {"rating": 1752, "rank": 12354}, "challenger": {"rating": 1535, "rank": 43155}, "rank_one": {"rating": 2617, "rank": 123}, "duelist": {"rating": 2003, "rank": 3714}, "glad": {"rating": 2355, "rank": 617}}}}}